solr_mcp/__init__.py
solr_mcp/server.py
solr_mcp/solr/__init__.py
solr_mcp/solr/client.py
solr_mcp/solr/collections.py
solr_mcp/solr/config.py
solr_mcp/solr/constants.py
solr_mcp/solr/exceptions.py
solr_mcp/solr/interfaces.py
solr_mcp/solr/query/__init__.py
solr_mcp/solr/query/builder.py
solr_mcp/solr/query/executor.py
solr_mcp/solr/query/parser.py
solr_mcp/solr/query/validator.py
solr_mcp/solr/response.py
solr_mcp/solr/schema/__init__.py
solr_mcp/solr/schema/cache.py
solr_mcp/solr/schema/fields.py
solr_mcp/solr/utils/__init__.py
solr_mcp/solr/utils/formatting.py
solr_mcp/solr/vector/__init__.py
solr_mcp/solr/vector/manager.py
solr_mcp/solr/vector/results.py
solr_mcp/solr/zookeeper.py
solr_mcp/tools/__init__.py
solr_mcp/tools/base.py
solr_mcp/tools/solr_default_vectorizer.py
solr_mcp/tools/solr_list_collections.py
solr_mcp/tools/solr_list_fields.py
solr_mcp/tools/solr_select.py
solr_mcp/tools/solr_semantic_select.py
solr_mcp/tools/solr_vector_select.py
solr_mcp/tools/tool_decorator.py
solr_mcp/utils.py
solr_mcp/vector_provider/__init__.py
solr_mcp/vector_provider/clients/__init__.py
solr_mcp/vector_provider/clients/ollama.py
solr_mcp/vector_provider/constants.py
solr_mcp/vector_provider/exceptions.py
solr_mcp/vector_provider/interfaces.py
mseep_solr_mcp-0.1.2.dist-info/LICENSE
mseep_solr_mcp-0.1.2.dist-info/METADATA
mseep_solr_mcp-0.1.2.dist-info/WHEEL
mseep_solr_mcp-0.1.2.dist-info/entry_points.txt
mseep_solr_mcp-0.1.2.dist-info/RECORD
