Metadata-Version: 2.3
Name: mseep-solr-mcp
Version: 0.1.2
Summary: A Python package for accessing Solr indexes via Model Context Protocol (MCP)
License: MIT
Author: mseep
Author-email: support@skydeck.ai
Maintainer: mseep
Maintainer-email: support@skydeck.ai
Requires-Python: >=3.10,<4.0
Classifier: License :: OSI Approved :: MIT License
Classifier: Programming Language :: Python :: 3
Classifier: Programming Language :: Python :: 3.10
Classifier: Programming Language :: Python :: 3.11
Classifier: Programming Language :: Python :: 3.12
Classifier: Programming Language :: Python :: 3.13
Requires-Dist: fastapi (>=0.109.2,<0.110.0)
Requires-Dist: httpx (>=0.27.0,<0.28.0)
Requires-Dist: kazoo (>=2.10.0,<3.0.0)
Requires-Dist: loguru (>=0.7.3,<0.8.0)
Requires-Dist: markdown (>=3.5.2,<4.0.0)
Requires-Dist: mcp (>=1.4.1,<2.0.0)
Requires-Dist: numpy (>=1.26.3,<2.0.0)
Requires-Dist: pydantic (>=2.6.1,<3.0.0)
Requires-Dist: pysolr (>=3.9.0,<4.0.0)
Requires-Dist: pytest-mock (>=3.14.0,<4.0.0)
Requires-Dist: python-frontmatter (>=1.1.0,<2.0.0)
Requires-Dist: sqlglot (>=26.11.1,<27.0.0)
Requires-Dist: uvicorn (>=0.27.1,<0.28.0)
